setup.py
wansuite/__init__.py
wansuite/investing.py
wansuite/iofile.py
wansuite/msql.py
wansuite/sys.py
wansuite/updateMacroData.py
wansuite/updateMarketData.py
wansuite/wtime.py
wansuite.egg-info/PKG-INFO
wansuite.egg-info/SOURCES.txt
wansuite.egg-info/dependency_links.txt
wansuite.egg-info/requires.txt
wansuite.egg-info/top_level.txt
wansuite/macrodata/__init__.py
wansuite/macrodata/updatefromfile.py
wansuite/marketdata/__init__.py
wansuite/marketdata/updateMarketData.py
wansuite/media/__init__.py
wansuite/media/datacollection.py
wansuite/media/datavis.py
wansuite/media/network.py
wansuite/media/nownews.py
wansuite/media/sentiment.py
wansuite/media/sys.py
wansuite/media/textfeature.py
wansuite/media/textprocessing.py
wansuite/media/topicmodel.py
wansuite/order/__init__.py
wansuite/strategy/__init__.py
wansuite/strategy/zack.py