Metadata-Version: 2.1
Name: wansuite
Version: 12.0
Summary: A Simplified Toolkits  
